edc_ltfu/__init__.py
edc_ltfu/action_items.py
edc_ltfu/admin.py
edc_ltfu/admin_site.py
edc_ltfu/apps.py
edc_ltfu/choices.py
edc_ltfu/constants.py
edc_ltfu/model_mixins.py
edc_ltfu/modeladmin_mixin.py
edc_ltfu/modelform_mixins.py
edc_ltfu/models.py
edc_ltfu/urls.py
edc_ltfu/utils.py
edc_ltfu/forms/__init__.py
edc_ltfu/forms/ltfu_form.py
edc_ltfu/forms/ltfu_form_validator.py
edc_ltfu/forms/ltfu_form_validator_mixin.py
edc_ltfu/migrations/__init__.py
edc_ltfu/tests/__init__.py
edc_ltfu/tests/consents.py
edc_ltfu/tests/forms.py
edc_ltfu/tests/holidays.csv
edc_ltfu/tests/models.py
edc_ltfu/tests/test_settings.py
edc_ltfu/tests/etc/user-aes-local.key
edc_ltfu/tests/etc/user-aes-restricted.key
edc_ltfu/tests/etc/user-rsa-local-private.pem
edc_ltfu/tests/etc/user-rsa-local-public.pem
edc_ltfu/tests/etc/user-rsa-restricted-private.pem
edc_ltfu/tests/etc/user-rsa-restricted-public.pem
edc_ltfu/tests/etc/user-salt-local.key
edc_ltfu/tests/etc/user-salt-restricted.key
edc_ltfu/tests/tests/__init__.py
edc_ltfu/tests/tests/test_ltfu.py
edc_ltfu-1.0.1.dist-info/LICENSE
edc_ltfu-1.0.1.dist-info/METADATA
edc_ltfu-1.0.1.dist-info/WHEEL
edc_ltfu-1.0.1.dist-info/top_level.txt
edc_ltfu-1.0.1.dist-info/RECORD
